agentmonitor/__init__.py
agentmonitor/async_client.py
agentmonitor/batcher.py
agentmonitor/client.py
agentmonitor/config.py
agentmonitor/decorators.py
agentmonitor/exceptions.py
agentmonitor/models.py
agentmonitor/monitor.py
agentmonitor/utils.py
agentmonitor-0.1.0.dist-info/licenses/LICENSE
agentmonitor-0.1.0.dist-info/METADATA
agentmonitor-0.1.0.dist-info/WHEEL
agentmonitor-0.1.0.dist-info/top_level.txt
agentmonitor-0.1.0.dist-info/RECORD
