Metadata-Version: 2.4
Name: agentmonitor
Version: 0.1.0
Summary: Production-ready SDK for monitoring AI agents
Home-page: https://github.com/agentmonitor/sdk-python
Author: AgentMonitor Team
Author-email: AgentMonitor Team <support@agentmonitor.io>
License: MIT
Project-URL: Homepage, https://github.com/agentmonitor/sdk-python
Project-URL: Documentation, https://docs.agentmonitor.io
Project-URL: Repository, https://github.com/agentmonitor/sdk-python
Project-URL: Issues, https://github.com/agentmonitor/sdk-python/issues
Keywords: ai,agent,monitoring,observability,analytics,ml,llm
Classifier: Development Status :: 4 - Beta
Classifier: Intended Audience :: Developers
Classifier: License :: OSI Approved :: MIT License
Classifier: Programming Language :: Python :: 3
Classifier: Programming Language :: Python :: 3.8
Classifier: Programming Language :: Python :: 3.9
Classifier: Programming Language :: Python :: 3.10
Classifier: Programming Language :: Python :: 3.11
Classifier: Programming Language :: Python :: 3.12
Classifier: Topic :: Software Development :: Libraries :: Python Modules
Classifier: Topic :: System :: Monitoring
Requires-Python: >=3.8
License-File: LICENSE
Requires-Dist: requests>=2.28.0
Requires-Dist: typing-extensions>=4.0.0
Provides-Extra: async
Requires-Dist: aiohttp>=3.8.0; extra == "async"
Provides-Extra: dev
Requires-Dist: pytest>=7.0.0; extra == "dev"
Requires-Dist: pytest-asyncio>=0.21.0; extra == "dev"
Requires-Dist: pytest-cov>=4.0.0; extra == "dev"
Requires-Dist: responses>=0.23.0; extra == "dev"
Requires-Dist: black>=23.0.0; extra == "dev"
Requires-Dist: flake8>=6.0.0; extra == "dev"
Requires-Dist: mypy>=1.0.0; extra == "dev"
Dynamic: author
Dynamic: home-page
Dynamic: license-file
Dynamic: requires-python
